resumyst/Makefile
resumyst/__init__.py
resumyst/cli.py
resumyst/editor.py
resumyst/server.py
resumyst/templates.py
resumyst/typst_installer.py
resumyst/validator.py
resumyst/wizard.py
resumyst/commands/__init__.py
resumyst/commands/build.py
resumyst/commands/init.py
resumyst/data/config.yaml
resumyst/data/personal.yaml
resumyst/data/sections/awards.yaml
resumyst/data/sections/education.yaml
resumyst/data/sections/experience.yaml
resumyst/data/sections/memberships.yaml
resumyst/data/sections/publication.yaml
resumyst/data/sections/reviewer.yaml
resumyst/data/sections/skills.yaml
resumyst/data/sections/supervision.yaml
resumyst/data/sections/talks.yaml
resumyst/data/sections/teaching.yaml
resumyst/data/variants/academic.yaml
resumyst/data/variants/industry.yaml
resumyst/data/variants/short.yaml
resumyst/typst/components.typ
resumyst/typst/config.typ
resumyst/typst/cv.typ
resumyst/typst/data.typ
resumyst/typst/renderers.typ
resumyst/typst/styles.typ
resumyst/typst/template.typ
resumyst-0.1.1.dist-info/entry_points.txt
resumyst-0.1.1.dist-info/licenses/LICENSE
resumyst-0.1.1.dist-info/WHEEL
resumyst-0.1.1.dist-info/METADATA
resumyst-0.1.1.dist-info/RECORD
