Metadata-Version: 2.4
Name: resumyst
Version: 0.1.1
Summary: Modern CV generation system combining Typst templating with Python CLI - create multiple professional document variants from unified YAML data
Keywords: cv,resume,typst,template,cli,yaml,document-generation,academic,pdf,professional
Author: Filippo Guerranti
Requires-Python: >=3.10
Classifier: Development Status :: 4 - Beta
Classifier: Intended Audience :: End Users/Desktop
Classifier: License :: OSI Approved :: MIT License
Classifier: Operating System :: OS Independent
Classifier: Programming Language :: Python :: 3
Classifier: Programming Language :: Python :: 3.10
Classifier: Programming Language :: Python :: 3.11
Classifier: Programming Language :: Python :: 3.12
Classifier: Topic :: Text Processing :: Markup
Classifier: Topic :: Office/Business
License-File: LICENSE
Requires-Dist: click>=8.0.0
Requires-Dist: pyyaml>=6.0.0
Requires-Dist: rich>=13.0.0
Requires-Dist: watchdog>=3.0.0
Project-URL: Homepage, https://github.com/guerrantif/resumyst
Project-URL: Issues, https://github.com/guerrantif/resumyst/issues
Project-URL: Repository, https://github.com/guerrantif/resumyst
